odoo/addons/ai_oca_bridge_fieldservice/README.rst
odoo/addons/ai_oca_bridge_fieldservice/__init__.py
odoo/addons/ai_oca_bridge_fieldservice/__manifest__.py
odoo/addons/ai_oca_bridge_fieldservice/demo/ai_bridge_demo.xml
odoo/addons/ai_oca_bridge_fieldservice/i18n/ai_oca_bridge_fieldservice.pot
odoo/addons/ai_oca_bridge_fieldservice/i18n/it.po
odoo/addons/ai_oca_bridge_fieldservice/models/__init__.py
odoo/addons/ai_oca_bridge_fieldservice/models/fsm_order.py
odoo/addons/ai_oca_bridge_fieldservice/readme/CONTRIBUTORS.md
odoo/addons/ai_oca_bridge_fieldservice/readme/DESCRIPTION.md
odoo/addons/ai_oca_bridge_fieldservice/static/description/icon.png
odoo/addons/ai_oca_bridge_fieldservice/static/description/icon.svg
odoo/addons/ai_oca_bridge_fieldservice/static/description/index.html
odoo/addons/ai_oca_bridge_fieldservice/tests/__init__.py
odoo/addons/ai_oca_bridge_fieldservice/tests/test_fsm_order_ai_bridge.py
odoo_addon_ai_oca_bridge_fieldservice-16.0.2.0.0.dist-info/METADATA
odoo_addon_ai_oca_bridge_fieldservice-16.0.2.0.0.dist-info/WHEEL
odoo_addon_ai_oca_bridge_fieldservice-16.0.2.0.0.dist-info/top_level.txt
odoo_addon_ai_oca_bridge_fieldservice-16.0.2.0.0.dist-info/RECORD
